isofit/__init__.py
isofit/__main__.py
isofit/configs/__init__.py
isofit/configs/base_config.py
isofit/configs/configs.py
isofit/configs/sections/__init__.py
isofit/configs/sections/forward_model_config.py
isofit/configs/sections/implementation_config.py
isofit/configs/sections/input_config.py
isofit/configs/sections/instrument_config.py
isofit/configs/sections/inversion_config.py
isofit/configs/sections/output_config.py
isofit/configs/sections/radiative_transfer_config.py
isofit/configs/sections/statevector_config.py
isofit/configs/sections/surface_config.py
isofit/core/__init__.py
isofit/core/common.py
isofit/core/fileio.py
isofit/core/forward.py
isofit/core/geometry.py
isofit/core/instrument.py
isofit/core/isofit.py
isofit/core/sunposition.py
isofit/core/units.py
isofit/data/__init__.py
isofit/data/build_examples.py
isofit/data/download.py
isofit/data/ini.py
isofit/data/shared.py
isofit/data/validate.py
isofit/data/cli/__init__.py
isofit/data/cli/data.py
isofit/data/cli/examples.py
isofit/data/cli/imagecube.py
isofit/data/cli/isoplots.py
isofit/data/cli/sixs.py
isofit/data/cli/srtmnet.py
isofit/debug/__init__.py
isofit/debug/ray_bypass.py
isofit/debug/resource_tracker.py
isofit/inversion/__init__.py
isofit/inversion/inverse.py
isofit/inversion/inverse_mcmc.py
isofit/inversion/inverse_simple.py
isofit/radiative_transfer/__init__.py
isofit/radiative_transfer/luts.py
isofit/radiative_transfer/radiative_transfer.py
isofit/radiative_transfer/radiative_transfer_engine.py
isofit/radiative_transfer/engines/__init__.py
isofit/radiative_transfer/engines/kernel_flows.py
isofit/radiative_transfer/engines/modtran.py
isofit/radiative_transfer/engines/sRTMnet.py
isofit/radiative_transfer/engines/six_s.py
isofit/radiative_transfer/engines/templates/full.py
isofit/radiative_transfer/engines/templates/minimal.py
isofit/surface/__init__.py
isofit/surface/surface.py
isofit/surface/surface_glint_model.py
isofit/surface/surface_lut.py
isofit/surface/surface_multicomp.py
isofit-3.5.1.dist-info/METADATA
isofit-3.5.1.dist-info/WHEEL
isofit-3.5.1.dist-info/entry_points.txt
isofit-3.5.1.dist-info/licenses/LICENSE
isofit-3.5.1.dist-info/RECORD
