Metadata-Version: 2.4
Name: isofit
Version: 3.5.1
Summary: Imaging Spectrometer Optimal FITting
Project-URL: repository, https://github.com/isofit/isofit
Project-URL: documentation, https://isofit.readthedocs.io/en/latest/index.html
Author-email: "David R. Thompson" <david.r.thompson@jpl.nasa.gov>, "Philip G. Brodrick" <philip.brodrick@jpl.nasa.gov>, Niklas Bohn <urs.n.bohn@jpl.nasa.gov>, Evan Greenberg <evan.greenberg@jpl.nasa.gov>, James Montgomery <J.Montgomery@jpl.nasa.gov>, Winston Olson-Duvall <winston.olson-duvall@jpl.nasa.gov>
Maintainer-email: "David R. Thompson" <david.r.thompson@jpl.nasa.gov>, "Philip G. Brodrick" <philip.brodrick@jpl.nasa.gov>, Niklas Bohn <urs.n.bohn@jpl.nasa.gov>, Evan Greenberg <evan.greenberg@jpl.nasa.gov>, James Montgomery <J.Montgomery@jpl.nasa.gov>
License: 
License-File: LICENSE
Keywords: isofit
Classifier: License :: OSI Approved :: Apache Software License
Classifier: Operating System :: OS Independent
Classifier: Programming Language :: Python :: 3.9
Classifier: Programming Language :: Python :: 3.10
Classifier: Programming Language :: Python :: 3.11
Classifier: Programming Language :: Python :: 3.12
Requires-Python: >=3.9
Requires-Dist: click
Requires-Dist: dask
Requires-Dist: h5py
Requires-Dist: netcdf4
Requires-Dist: numpy>=1.20
Requires-Dist: pandas>=0.24.0
Requires-Dist: pyyaml>=5.3.2
Requires-Dist: ray>=1.2.0
Requires-Dist: scikit-image>=0.17.0
Requires-Dist: scikit-learn>=0.19.1
Requires-Dist: scipy>=1.3.0
Requires-Dist: spectral>=0.19
Requires-Dist: utm
Requires-Dist: xarray
Requires-Dist: xxhash>=1.2.0
Provides-Extra: dev
Requires-Dist: black; extra == 'dev'
Requires-Dist: isort; extra == 'dev'
Requires-Dist: pre-commit; extra == 'dev'
Provides-Extra: docker
Requires-Dist: ipykernel; extra == 'docker'
Requires-Dist: ipywidgets; extra == 'docker'
Requires-Dist: matplotlib; extra == 'docker'
Provides-Extra: docs
Requires-Dist: myst-parser; extra == 'docs'
Requires-Dist: sphinx-autoapi; extra == 'docs'
Requires-Dist: sphinx-rtd-theme; extra == 'docs'
Provides-Extra: test
Requires-Dist: pytest>=3.5.1; extra == 'test'
